shuup_channels/__init__.py
shuup_channels/apps.py
shuup_channels/routing.py
shuup_channels-1.0.1.dist-info/METADATA
shuup_channels-1.0.1.dist-info/RECORD
shuup_channels-1.0.1.dist-info/WHEEL
shuup_channels-1.0.1.dist-info/entry_points.txt
shuup_channels-1.0.1.dist-info/top_level.txt
