Metadata-Version: 2.1
Name: shuup-channels
Version: 1.0.1
Summary: Enables the power of WebSockets with Django Channels in Shuup Ecommerce Platform.
Home-page: https://github.com/chessbr/shuup-channels
Author: Christian Hess
Author-email: UNKNOWN
License: MIT
Keywords: shuup websocket channels
Platform: UNKNOWN
Requires-Dist: shuup
Requires-Dist: channels
